primesw/__init__.py
primesw/prime.py
primesw/prime_v0.1.0.keras
primesw/primeinsc_v0.1.0.pkl
primesw/primesh.py
primesw/primesh_v0.1.0.keras
primesw/primeshinsc_v0.1.0.pkl
primesw/primeshlocsc_v0.1.0.pkl
primesw/primeshtarsc_v0.1.0.pkl
primesw/primetarsc_v0.1.0.pkl
primesw-0.5.0.dist-info/LICENSE
primesw-0.5.0.dist-info/METADATA
primesw-0.5.0.dist-info/WHEEL
primesw-0.5.0.dist-info/RECORD
