Metadata-Version: 2.1
Name: primesw
Version: 0.5.0
Summary: Probabilistic Regressor for Input to the Magnetosphere Estimation (Solar Wind)
License: GPL-3.0
Author: Connor OBrien
Author-email: obrienco@bu.edu
Requires-Python: >=3.8,<3.11
Classifier: Development Status :: 4 - Beta
Classifier: License :: OSI Approved :: GNU General Public License v3 (GPLv3)
Classifier: Programming Language :: Python :: 3
Classifier: Programming Language :: Python :: 3.8
Classifier: Programming Language :: Python :: 3.9
Classifier: Programming Language :: Python :: 3.10
Classifier: Topic :: Scientific/Engineering :: Astronomy
Classifier: Topic :: Scientific/Engineering :: Atmospheric Science
Classifier: Topic :: Scientific/Engineering :: Physics
Requires-Dist: cdasws (>=1.8.9,<2.0.0)
Requires-Dist: cdflib (>=1.3.2,<2.0.0)
Requires-Dist: matplotlib (>=3.4)
Requires-Dist: numpy (>=1.20.3,<2.0.0)
Requires-Dist: pandas (>=1.2,<2.0)
Requires-Dist: protobuf (==3.20.0)
Requires-Dist: scikit-learn (>=0.24)
Requires-Dist: scipy (>=1.6)
Requires-Dist: tables (>=3.8.0,<4.0.0)
Requires-Dist: tensorflow (>=2.8.0,<3.0.0)
Requires-Dist: tensorflow-io-gcs-filesystem (==0.25.0)
Requires-Dist: xarray (>=2023.1.0,<2024.0.0)
